gemseo_benchmark/__init__.py
gemseo_benchmark/scenario.py
gemseo_benchmark/algorithms/__init__.py
gemseo_benchmark/algorithms/algorithm_configuration.py
gemseo_benchmark/algorithms/algorithms_configurations.py
gemseo_benchmark/benchmarker/__init__.py
gemseo_benchmark/benchmarker/_metrics.py
gemseo_benchmark/benchmarker/base_worker.py
gemseo_benchmark/benchmarker/benchmarker.py
gemseo_benchmark/benchmarker/mda_worker.py
gemseo_benchmark/benchmarker/mdo_worker.py
gemseo_benchmark/benchmarker/optimization_worker.py
gemseo_benchmark/data_profiles/__init__.py
gemseo_benchmark/data_profiles/data_profile.py
gemseo_benchmark/data_profiles/target_values.py
gemseo_benchmark/data_profiles/targets_generator.py
gemseo_benchmark/problems/__init__.py
gemseo_benchmark/problems/base_problem_configuration.py
gemseo_benchmark/problems/mda_problem_configuration.py
gemseo_benchmark/problems/mdo_problem_configuration.py
gemseo_benchmark/problems/optimization_problem_configuration.py
gemseo_benchmark/problems/problems_group.py
gemseo_benchmark/report/__init__.py
gemseo_benchmark/report/_figures.py
gemseo_benchmark/report/axis_data.py
gemseo_benchmark/report/conf.py
gemseo_benchmark/report/range_plot.py
gemseo_benchmark/report/report.py
gemseo_benchmark/report/report_plot.py
gemseo_benchmark/report/templates/algorithm_configuration_results.rst
gemseo_benchmark/report/templates/algorithms.rst
gemseo_benchmark/report/templates/algorithms_configurations_group.rst
gemseo_benchmark/report/templates/index.rst
gemseo_benchmark/report/templates/problem.rst
gemseo_benchmark/report/templates/problem_results.rst
gemseo_benchmark/report/templates/problems_list.rst
gemseo_benchmark/report/templates/results.rst
gemseo_benchmark/report/templates/sub_results.rst
gemseo_benchmark/results/__init__.py
gemseo_benchmark/results/history_item.py
gemseo_benchmark/results/performance_histories.py
gemseo_benchmark/results/performance_history.py
gemseo_benchmark/results/results.py
gemseo_benchmark-4.0.1.dist-info/licenses/LICENSE.txt
gemseo_benchmark-4.0.1.dist-info/METADATA
gemseo_benchmark-4.0.1.dist-info/WHEEL
gemseo_benchmark-4.0.1.dist-info/top_level.txt
gemseo_benchmark-4.0.1.dist-info/RECORD
